stockDL/__init__.py
stockDL/__main__.py
stockDL/calculations.py
stockDL/data.py
stockDL/main.py
stockDL/market.py
stockDL/models.py
stockDL/plots.py
stockDL/preprocessing.py
stockDL/results.py
stockDL/train.py
stockDL-0.2.5.dist-info/LICENSE.md
stockDL-0.2.5.dist-info/METADATA
stockDL-0.2.5.dist-info/WHEEL
stockDL-0.2.5.dist-info/entry_points.txt
stockDL-0.2.5.dist-info/top_level.txt
stockDL-0.2.5.dist-info/RECORD
