Metadata-Version: 2.1
Name: stockDL
Version: 0.2.5
Summary: Predicts the Gross Yield, Annual Yield and Net Yield of a user given stock ticker.
Home-page: https://github.com/ashishpapanai/stockDL
Author: Ashish Papanai
Author-email: ashishpapanai00@gmail.com
License: MIT
Platform: UNKNOWN
Classifier: License :: OSI Approved :: MIT License
Classifier: Programming Language :: Python :: 3.6
Classifier: Programming Language :: Python :: 3.7
Classifier: Programming Language :: Python :: 3.8
License-File: LICENSE.md
Requires-Dist: pandas
Requires-Dist: numpy
Requires-Dist: matplotlib
Requires-Dist: keras
Requires-Dist: tensorflow
Requires-Dist: yahoo-finance
Requires-Dist: yfinance
